bnmutils/__init__.py
bnmutils/__version__.py
bnmutils/configparser.py
bnmutils/exceptions.py
bnmutils/novelty.py
bnmutils-1.0.3.dist-info/METADATA
bnmutils-1.0.3.dist-info/RECORD
bnmutils-1.0.3.dist-info/WHEEL
bnmutils-1.0.3.dist-info/top_level.txt
