Metadata-Version: 2.1
Name: bnmutils
Version: 1.0.3
Summary: Compilations of various utilities
Home-page: https://github.com/BNMetrics/bnmetrics-utils
Author: Luna Chen
Author-email: luna@bnmetrics.com
License: Apache 2.0
Keywords: configparser,.ini,docstring
Platform: UNKNOWN
Requires-Python: >=3
